mem_utils/__init__.py
mem_utils/string/__init__.py
mem_utils/string/formatage.py
mem_utils-0.10.1.dist-info/licenses/LICENSE
mem_utils-0.10.1.dist-info/METADATA
mem_utils-0.10.1.dist-info/WHEEL
mem_utils-0.10.1.dist-info/top_level.txt
mem_utils-0.10.1.dist-info/RECORD
