Metadata-Version: 2.4
Name: mem_utils
Version: 0.10.1
Summary: Outil CLI de gestion complète du cycle de vie d’un projet Python
Author-email: Guillaume Lefebvre <guillaume@ldmail.fr>
License: MIT License
Requires-Python: >=3.8
License-File: LICENSE
Provides-Extra: dev
Requires-Dist: typer[all]; extra == "dev"
Requires-Dist: rich; extra == "dev"
Requires-Dist: python-dotenv; extra == "dev"
Requires-Dist: pytest; extra == "dev"
Requires-Dist: build; extra == "dev"
Requires-Dist: twine; extra == "dev"
Dynamic: license-file
